README.md
jira_context.py
setup.py
jira_context.egg-info/PKG-INFO
jira_context.egg-info/SOURCES.txt
jira_context.egg-info/dependency_links.txt
jira_context.egg-info/requires.txt
jira_context.egg-info/top_level.txt
jira_context.egg-info/zip-safe