Metadata-Version: 1.1
Name: jira-context
Version: 1.0.0
Summary: Cache JIRA basic authentication sessions to disk for console apps.
Home-page: https://github.com/Robpol86/jira-context
Author: @Robpol86
Author-email: robpol86@gmail.com
License: MIT
Keywords: jira
Platform: UNKNOWN
Classifier: Development Status :: 5 - Production/Stable
Classifier: Environment :: Console
Classifier: Environment :: MacOS X
Classifier: Intended Audience :: Developers
Classifier: License :: OSI Approved :: MIT License
Classifier: Operating System :: MacOS :: MacOS X
Classifier: Operating System :: POSIX
Classifier: Operating System :: POSIX :: Linux
Classifier: Programming Language :: Python :: 2.6
Classifier: Programming Language :: Python :: 2.7
Classifier: Programming Language :: Python :: 3.3
Classifier: Programming Language :: Python :: 3.4
Classifier: Topic :: Software Development :: Libraries
Classifier: Topic :: Text Processing :: Markup
